requests_glob.py
requests_glob-0.3.2.dist-info/METADATA
requests_glob-0.3.2.dist-info/WHEEL
requests_glob-0.3.2.dist-info/licenses/LICENSE
requests_glob-0.3.2.dist-info/RECORD
