Metadata-Version: 2.4
Name: requests-glob
Version: 0.3.2
Summary: File transport adapter for Requests
Project-URL: Homepage, https://github.com/huakim/python-requests-glob
Author-email: David Shea <reallylongword@gmail.com>
License: Apache 2.0
License-File: LICENSE
Classifier: Development Status :: 3 - Alpha
Classifier: Environment :: Plugins
Classifier: Intended Audience :: Developers
Classifier: License :: OSI Approved :: Apache Software License
Classifier: Programming Language :: Python :: 3
Requires-Dist: glob2>=0.1
Requires-Dist: requests>=1.0.0
Requires-Dist: sortedcontainers>=1.0.0
